{"data":{"allMdx":{"edges":[{"node":{"fields":{"slug":"/","title":"About"}}},{"node":{"fields":{"slug":"/React-programming","title":"실전 리엑트 프로그래밍"}}},{"node":{"fields":{"slug":"/deploy_team_blog","title":"Github Action으로 Gatsby 블로그 배포하기"}}},{"node":{"fields":{"slug":"/kafka-streams","title":"데이터 가공의 또다른 방식 Stream Processing"}}},{"node":{"fields":{"slug":"/npm-package-publish","title":"NPM 모듈 패키지 제작 및 배포"}}},{"node":{"fields":{"slug":"/react-redux","title":"REACT REDUX"}}},{"node":{"fields":{"slug":"/React-programming/1","title":"실전 리엑트 프로그래밍 1장"}}},{"node":{"fields":{"slug":"/React-programming/2","title":"실전 리엑트 프로그래밍 2장"}}},{"node":{"fields":{"slug":"/React-programming/3","title":"실전 리엑트 프로그래밍 3장"}}},{"node":{"fields":{"slug":"/kafka-streams/1","title":"Stream Processing 특징"}}},{"node":{"fields":{"slug":"/kafka-streams/2","title":"카프카 로컬 설치"}}},{"node":{"fields":{"slug":"/npm-package-publish/j3d-npm-sample","title":"샘플 모듈 패키지 NPM 배포해보기"}}},{"node":{"fields":{"slug":"/react-redux/1","title":"React Redux - Core Concept"}}}]}}}